data_stream.py
data_stream/__init__.py
data_stream/data_stream.py
src/__init__.py
src/data_stream.py
data_streaming-1.0.dist-info/LICENSE
data_streaming-1.0.dist-info/METADATA
data_streaming-1.0.dist-info/WHEEL
data_streaming-1.0.dist-info/entry_points.txt
data_streaming-1.0.dist-info/top_level.txt
data_streaming-1.0.dist-info/RECORD
