Metadata-Version: 2.1
Name: data-streaming
Version: 1.0
Summary: Data Stream
Home-page: https://github.com/WalBouss/data_stream
Author: Walid Bousselham
Author-email: 
Keywords: Data Stream
Classifier: Development Status :: 3 - Alpha
Classifier: Intended Audience :: Education
Classifier: Intended Audience :: Science/Research
Classifier: License :: OSI Approved :: Apache Software License
Classifier: Programming Language :: Python :: 3.7
Classifier: Programming Language :: Python :: 3.8
Classifier: Programming Language :: Python :: 3.9
Classifier: Programming Language :: Python :: 3.10
Classifier: Programming Language :: Python :: 3.11
Classifier: Programming Language :: Python :: 3.12
Classifier: Topic :: Scientific/Engineering
Classifier: Topic :: Scientific/Engineering :: Artificial Intelligence
Classifier: Topic :: Software Development
Classifier: Topic :: Software Development :: Libraries
Classifier: Topic :: Software Development :: Libraries :: Python Modules
Requires-Python: >=3.7
License-File: LICENSE
Requires-Dist: uvicorn
Requires-Dist: fastapi
Requires-Dist: httpx
Requires-Dist: sshtunnel
Requires-Dist: paramiko
Requires-Dist: pydantic
Requires-Dist: pydantic-settings
Requires-Dist: argparse
